zippy/__init__.py
zippy/__init__.pyc
zippy/bcl2fastq.py
zippy/bcl2fastq.pyc
zippy/bloom_kmer_finder.py
zippy/build_all.spec
zippy/bwa.py
zippy/bwa.pyc
zippy/deseq.r
zippy/downsampling_bloom.py
zippy/edger.r
zippy/make_params.py
zippy/make_params.pyc
zippy/modular_helper.py
zippy/modular_helper.pyc
zippy/modular_runner.py
zippy/modular_runner.pyc
zippy/params.py
zippy/params.pyc
zippy/primer_dimer_miner.py
zippy/rna_stats.py
zippy/run_edger.py
zippy/samplesheet.py
zippy/samplesheet.pyc
zippy/star.py
zippy/star.pyc
zippy/utils.py
zippy/utils.pyc
zippy/zippy.py
zippy/zippy.pyc
zippy/examples/chipseq.json
zippy/examples/docker.json
zippy/examples/rna.json
zippy/examples/subworkflow.json
zippy/examples/subworkflow_down.json
zippy/test/OtherRunner.py
zippy/test/defaults.json
zippy/test/defaults_ignore.json
zippy/test/defaults_include.json
zippy/test/defaults_test.proto
zippy/test/defaults_warn.json
zippy/test/dummy_params_test.json
zippy/test/environment_params_test.json
zippy/test/import_test.json
zippy/test/import_test.proto
zippy/test/merge_and_macs.json
zippy/test/merge_and_macs.proto
zippy/test/rsem.json
zippy/test/rsem.proto
zippy/test/subworkflow_params_test.json
zippy/test/test_defaults.json
zippy/test/test_make_params.py
zippy/test/test_params.py
zippy_pipeline-2.1.3.0.dist-info/LICENSE
zippy_pipeline-2.1.3.0.dist-info/METADATA
zippy_pipeline-2.1.3.0.dist-info/WHEEL
zippy_pipeline-2.1.3.0.dist-info/dependency_links.txt
zippy_pipeline-2.1.3.0.dist-info/top_level.txt
zippy_pipeline-2.1.3.0.dist-info/RECORD
