Metadata-Version: 2.1
Name: zippy-pipeline
Version: 2.1.3.0
Summary: NGS Pipeline Prototyping Tool for Python
Home-page: https://github.com/Illumina/zippy
Author: Aaron Wise
Author-email: quejebo@gmail.com
License: Apache 2.0
Download-URL: https://github.com/Illumina/zippy/archive/2.1.3.tar.gz
Platform: UNKNOWN
Requires-Dist: commentjson
Requires-Dist: pybloomfiltermmap
Requires-Dist: pyflow (>=1.1.0)
